hyohyo_game/__init__.py
hyohyo_game/christmas_runner.py
hyohyo_game/guess_number.py
hyohyo_game/number_baseball.py
hyohyo_game/rock_paper_scissors_console.py
hyohyo_game/ski_adventure.py
hyohyo_game-0.2.1.dist-info/METADATA
hyohyo_game-0.2.1.dist-info/WHEEL
hyohyo_game-0.2.1.dist-info/licenses/LICENSE
hyohyo_game-0.2.1.dist-info/RECORD
