Metadata-Version: 2.3
Name: hyohyo_game
Version: 0.2.1
Summary: Simple game package with console and pygame games
Project-URL: Homepage, https://github.com/glassesholder/hyohyo_game
Project-URL: Source, https://github.com/glassesholder/hyohyo_game
Author-email: Hyojun Lee <statisticlee@gmail.com>
License: MIT License
Keywords: console,entertainment,game,korean,pygame
Classifier: Development Status :: 4 - Beta
Classifier: Intended Audience :: End Users/Desktop
Classifier: License :: OSI Approved :: MIT License
Classifier: Operating System :: OS Independent
Classifier: Programming Language :: Python :: 3
Classifier: Programming Language :: Python :: 3.9
Classifier: Programming Language :: Python :: 3.10
Classifier: Programming Language :: Python :: 3.11
Classifier: Programming Language :: Python :: 3.12
Classifier: Topic :: Games/Entertainment
Requires-Python: >=3.9
Requires-Dist: pygame>=2.6.1
